{
  "scenario_name": "delayed_sensor",
  "first_divergence_step": 38,
  "first_divergence_time_s": 3.9,
  "expected_error_at_divergence": 0.720307,
  "actual_error_at_divergence": 1.50198,
  "error_growth_after_divergence": 0.903344,
  "max_position_error": 2.40532,
  "missed_deadlines": 0,
  "output_clipping_detected": true,
  "state_estimate_drift_detected": true,
  "unstable_oscillation_detected": true,
  "max_loop_elapsed_ms": 65,
  "avg_loop_elapsed_ms": 59.9375,
  "max_timing_jitter_ms": 0,
  "root_cause_classes": ["actuator_saturation","controller_output_clipping","delayed_measurement","dropped_sensor_sample","stale_state_estimate","state_estimate_drift","unstable_oscillation"]
}
